{
  "version": 0.1,
  "locale": "pt",
  "entries": {
    "8818ca53e31c": "Criar aplicação Next",
    "86dbb9f023f2": "Gerado por create next app",
    "ca249b2e1178": "Inglês",
    "54bfb1c34306": "العربية",
    "23d8867a1473": "Francês",
    "728e89b4515b": "Espanhol",
    "a850b7d69d12": "Português",
    "2aa81c111b69": "Russo",
    "28b5b8be2d38": "Chinês",
    "073e4b8dc80f": "Hindi",
    "498bde000b56": "Logótipo Next.js",
    "9ad922c5a3f9": "Para começar, edite o ficheiro page.tsx.",
    "fe51bf1cf1b4": "À procura de um ponto de partida ou mais instruções? Aceda a <a0>Modelos </a0> ou ao centro de <a1>Aprendizagem</a1>.",
    "cabbfb341ef3": "Implementar agora",
    "706150d051d0": "Marca Vercel",
    "61bb762097c1": "Documentação"
  }
}